oxitrait/__init__.py
oxitrait/enum.py
oxitrait/errors.py
oxitrait/impl.py
oxitrait/runtime.py
oxitrait/struct.py
oxitrait/trait.py
oxitrait-0.0.6.dist-info/licenses/LICENSE.txt
oxitrait-0.0.6.dist-info/licenses/NOTICE
oxitrait-0.0.6.dist-info/METADATA
oxitrait-0.0.6.dist-info/WHEEL
oxitrait-0.0.6.dist-info/top_level.txt
oxitrait-0.0.6.dist-info/RECORD
