Metadata-Version: 2.4
Name: oxitrait
Version: 0.0.6
Summary: A oxidized trait system for modern Python
Author-email: HeroesLament <heroeslament@nunya.biz>
License: 
Project-URL: Source Code, https://github.com/HeroesLament/oxitrait
Project-URL: Issues, https://github.com/HeroesLament/oxitrait/issues
Keywords: traits,rust,enums,metaclass,abc,dataclass
Classifier: Development Status :: 3 - Alpha
Classifier: Intended Audience :: Developers
Classifier: Topic :: Software Development :: Libraries :: Python Modules
Classifier: Programming Language :: Python :: 3.9
Classifier: Programming Language :: Python :: 3.10
Classifier: Programming Language :: Python :: 3.11
Classifier: Programming Language :: Python :: 3.12
Classifier: Programming Language :: Python :: 3.13
Requires-Python: >=3.9
License-File: LICENSE.txt
License-File: NOTICE
Provides-Extra: test
Requires-Dist: pytest>=8.3.5; extra == "test"
Dynamic: license-file
